<?xml version="1.0" encoding="UTF-8"?>
<template>
    <t t-name="twitter_tweets" name="res">
        <div class="col-md-12 oe_tweets">
            <div class="col-md-1 oe_padding">
                <img class="img-rounded oe_profile_image" t-att-src="res.user_image_url"></img>
            </div>
            <div class="col-md-11">
                <div>
                    <b><t t-raw="res.name"/></b>
                    <small>@<t t-raw="res.screen_name"/></small>
                    <span class="oe_formated_date pull-right"><t t-raw="res.created_at_formated_date"></t></span>
                </div>
                <div>
                    <p style="font-size:20px"><t t-raw="res.tweet"></t></p>
                </div>
                <div t-if="res.tweet_media_ids">
                    <t t-foreach="res.tweet_media_ids" t-as="res_media">
                      <img t-attf-src="#{res_media.media_url}:medium" height="{res_media.media_height}" width="{res_media.media_width}"></img>
                    </t>
                </div>
            </div>
        </div>
        <!-- <div class="row-fluid oe_tweets">
            <div class="col-md-12">
                <div class="col-md-1 oe_padding">
                    <img class="img-rounded oe_profile_image" t-att-src="res.user_image_url"></img>
                </div>
                <div class="col-md-11 oe_padding">
                    <div class="oe_user_name">
                        <h4><t t-raw="res.name"/>
                        <small class="text-muted">@<t t-raw="res.screen_name"/></small>
                        <span class="oe_formated_date pull-right text-muted"><t t-raw="res.created_at_formated_date"></t></span>
                        </h4>
                    </div>
                    <h3 class="oe_tweet_text"><t t-raw="res.tweet"></t></h3>
                    <div t-if="res.tweet_media_ids">
                        <t t-foreach="res.tweet_media_ids" t-as="res_media">
                            <img class="img-rounded" t-attf-src="#{res_media.media_url}:medium"></img>
                        </t>
                    </div>
                </div>
            </div>
        </div> -->
     </t>
     
     <t t-name="twitter_load_tweets">
     </t>
     
     <t t-name="twitter_moderate_tweets">
       <tr data-type="tweet" t-att-data-id="tweet.id" t-att-class="color_class">
        <td>
            <img t-attf-src="#{tweet.user_image_url}" alt="Media Thumbnail"  width="42" height="42"/>
        </td>
        <td>
            <t t-esc="tweet.name" />
        </td>
        <td>
            <t t-esc="tweet.description" />
        </td>
        <td>
            <t t-if="tweet.urls" t-foreach="tweet.urls" t-as="url">
                <a t-attf-href="#{url}" target="_blank">
                    <button type="submit" class="btn btn-default btn-sm"><i class="glyphicon glyphicon-globe" /></button>
                </a>
            </t>
        </td>
        <td>
            <t t-if="tweet.media">
                <img t-attf-src="#{tweet.media}" width="45" height="45" alt="Tweet Link" class="media_thumb" />
                <img t-attf-src="#{tweet.media}" alt="Original Media Thumbnail" class="media_inlarge"/>
            </t>
        </td>
        <td>
            <button type="submit" class="btn btn-default btn-sm rowremove" value="published"><i class="glyphicon glyphicon-ok" /></button>
            <button type="submit" class="btn btn-default btn-sm rowremove" value="unpublished"><i class="glyphicon glyphicon-remove" /></button>
        </td>
        <td>
            <img class="upload_img media_thumb pointer" t-att-src="'/website/image?model=website.twitter.wall.tweet&amp;field=back_image&amp;id='+tweet.id" width="42" height="42"/>
        </td>
       </tr>
     </t>
</template>
